print/__init__.py
print/print.py
septup-1.0.dist-info/METADATA
septup-1.0.dist-info/WHEEL
septup-1.0.dist-info/top_level.txt
septup-1.0.dist-info/RECORD
