Metadata-Version: 2.1
Name: septup
Version: 1.0
Summary: testing hosted app
Home-page: UNKNOWN
Author: ashok
Author-email: ashoklondhe.in@gmail.com
License: internal
Platform: UNKNOWN
